ymir_exc/__init__.py
ymir_exc/dataset_reader.py
ymir_exc/env.py
ymir_exc/monitor.py
ymir_exc/result_writer.py
ymir_exc/settings.py
ymir_exc-1.1.0.523.dist-info/METADATA
ymir_exc-1.1.0.523.dist-info/WHEEL
ymir_exc-1.1.0.523.dist-info/top_level.txt
ymir_exc-1.1.0.523.dist-info/RECORD
